Workbook

Sheet P&L Summary
A1: Vastra Junction – P&L Summary (FY 2023-2025)
A3: Category | B3: Net Revenue | C3: COGS | D3: Gross Profit | E3: Gross Margin %
A4: Womenswear | B4: 5411562 | C4: 3505759 | D4: ='P&L Summary'!$B4-'P&L Summary'!$C4 -> 1905803 | E4: ='P&L Summary'!$D4/'P&L Summary'!$B4 -> 0.35217244
A5: Footwear | B5: 4157866 | C5: 2894078 | D5: ='P&L Summary'!$B5-'P&L Summary'!$C5 -> 1263788 | E5: ='P&L Summary'!$D5/'P&L Summary'!$B5 -> 0.30395111
A6: Menswear | B6: 3597071 | C6: 2205797 | D6: ='P&L Summary'!$B6-'P&L Summary'!$C6 -> 1391274 | E6: ='P&L Summary'!$D6/'P&L Summary'!$B6 -> 0.38677969
A7: Accessories | B7: 3491305 | C7: 2342499 | D7: ='P&L Summary'!$B7-'P&L Summary'!$C7 -> 1148806 | E7: ='P&L Summary'!$D7/'P&L Summary'!$B7 -> 0.32904773
A8: Kidswear | B8: 1328743 | C8: 809528 | D8: ='P&L Summary'!$B8-'P&L Summary'!$C8 -> 519215 | E8: ='P&L Summary'!$D8/'P&L Summary'!$B8 -> 0.39075653
A9: Total | B9: =SUM(B4:B8) -> 17986547 | C9: =SUM(C4:C8) -> 11757661 | D9: ='P&L Summary'!$B9-'P&L Summary'!$C9 -> 6228886 | E9: ='P&L Summary'!$D9/'P&L Summary'!$B9 -> 0.34630805
A11: Company Operating P&L
A12: Total Net Revenue | B12: =B9 -> 17986547
A13: Total Gross Profit | B13: =D9 -> 6228886
A14: Less: Operating Expenses
A15: Rent & Occupancy | B15: =$B$12*Assumption!$B$2 -> 1798654.7
A16: Salaries & Staff | B16: =$B$12*Assumption!$B$3 -> 1438923.8
A17: Marketing | B17: =$B$12*Assumption!$B$4 -> 719461.88
A18: Logistics & Distribution | B18: =$B$12*Assumption!$B$5 -> 539596.41
A19: Admin & Other | B19: =$B$12*Assumption!$B$6 -> 539596.41
A20: Total Operating Expenses | B20: =SUM(B15:B19) -> 5036233.2
A21: Operating Profit (EBIT) | B21: =B13-B20 -> 1192652.8
A22: Operating Margin % | B22: =B21/B12 -> 0.066308049
A24: "Source: Vastra Junction sales data 2023–2025 · figures in ₹."
A25: Note: "Operating expenses modelled as % of net revenue (see Assumptions) ---> illustrative, not actual"

Sheet Trend & Forecast
A1: Month | B1: Revenue | C1: Forecast
A2: 44927 | B2: 372237
A3: 44958 | B3: 231407
A4: 44986 | B4: 469500
A5: 45017 | B5: 385410
A6: 45047 | B6: 480468
A7: 45078 | B7: 400254
A8: 45108 | B8: 352678
A9: 45139 | B9: 610526
A10: 45170 | B10: 524766
A11: 45200 | B11: 675655
A12: 45231 | B12: 568493
A13: 45261 | B13: 497646
... A37: 45992 | B37: 656876
A38: =EDATE(A37,1) -> 46023 | C38: =ROUND(_xlfn.FORECAST.ETS(A38, $B$2:$B$37, $A$2:$A$37, 1), 0) -> 450991
A39: =EDATE(A38,1) -> 46054 | C39: =ROUND(_xlfn.FORECAST.ETS(A39, $B$2:$B$37, $A$2:$A$37, 1), 0) -> 620649
A40: =EDATE(A39,1) -> 46082 | C40: =ROUND(_xlfn.FORECAST.ETS(A40, $B$2:$B$37, $A$2:$A$37, 1), 0) -> 614563
A41: =EDATE(A40,1) -> 46113 | C41: =ROUND(_xlfn.FORECAST.ETS(A41, $B$2:$B$37, $A$2:$A$37, 1), 0) -> 676350
A42: =EDATE(A41,1) -> 46143 | C42: =ROUND(_xlfn.FORECAST.ETS(A42, $B$2:$B$37, $A$2:$A$37, 1), 0) -> 667482
A43: =EDATE(A42,1) -> 46174 | C43: =ROUND(_xlfn.FORECAST.ETS(A43, $B$2:$B$37, $A$2:$A$37, 1), 0) -> 557794

Sheet Scenario Analysis
A1: Vastra Junction – Scenario Analysis: Discount Policy Impact
A3: Scenario | B3: Gross Margin Shift (pts)
A4: Base | B4: 0
A5: Optimistic | B5: 0.03
A6: Pessimistic | B6: -0.03
A8: Selected Scenario: | B8: Optimistic
A9: Margin shift applied: | B9: =VLOOKUP(B8,$A$4:$B$6,2,FALSE) -> 0.03
A12: Net Revenue | B12: ='P&L Summary'!$B$9 -> 17986547
A13: Base Gross Margin % | B13: ='P&L Summary'!$E$9 -> 0.34630805
A14: Scenario Gross Margin % | B14: =B13+B9 -> 0.37630805
A15: Scenario Gross Profit | B15: =B12*B14 -> 6768482.4
A16: Operating Expenses | B16: =B12*Assumption!$B$7 -> 5036233.2
A17: Operating Profit (EBIT) | B17: =B15-B16 -> 1732249.2
A18: Operating Margin % | B18: =B17/B12 -> 0.096308049
D20: Scenario | E20: EBIT
D21: Base | E21: =B12*(B13+$B$4)-B16 -> 1192652.8
D22: Optimistic | E22: =B12*(B13+$B$5)-B16 -> 1732249.2
D23: Pessimistic | E23: =B12*(B13+$B$6)-B16 -> 653056.43

Sheet Assumption
A1: Operating Expense Assumptions (% of net revenue) | B1: Opex %
A2: Rent & Occupancy | B2: 0.1
A3: Salaries & Staff | B3: 0.08
A4: Marketing | B4: 0.04
A5: Logistics & Distribution | B5: 0.03
A6: Admin & Other | B6: 0.03
A7: Total Opex % | B7: =SUM(B2:B6) -> 0.28

Sheet  Data 
A1: Data_Category | F1: Data_Monthly
A2: category | B2: net_revenue | C2: cogs | D2: gross_profit | F2: month | G2: net_revenue | H2: gross_profit
A3: Womenswear | B3: 5411562 | C3: 3505759 | D3: 1905803 | F3: 44927 | G3: 372237 | H3: 27434
A4: Footwear | B4: 4157866 | C4: 2894078 | D4: 1263788 | F4: 44958 | G4: 231407 | H4: 94126
A5: Menswear | B5: 3597071 | C5: 2205797 | D5: 1391274 | F5: 44986 | G5: 469500 | H5: 193365
A6: Accessories | B6: 3491305 | C6: 2342499 | D6: 1148806 | F6: 45017 | G6: 385410 | H6: 157698
A7: Kidswear | B7: 1328743 | C7: 809528 | D7: 519215 | F7: 45047 | G7: 480468 | H7: 195508
A8: Total | B8: =SUM(B3:B7) -> 17986547 | C8: =SUM(C3:C7) -> 11757661 | D8: =SUM(D3:D7) -> 6228886 | F8: 45078 | G8: 400254 | H8: 156180
F9: 45108 | G9: 352678 | H9: 34437
F10: 45139 | G10: 610526 | H10: 240213
F11: 45170 | G11: 524766 | H11: 202571
F12: 45200 | G12: 675655 | H12: 239715
F13: 45231 | G13: 568493 | H13: 200759
F14: 45261 | G14: 497646 | H14: 184095
F15: 45292 | G15: 372171 | H15: 32168
F16: 45323 | G16: 412667 | H16: 165432
F17: 45352 | G17: 457719 | H17: 187285
F18: 45383 | G18: 569683 | H18: 234057
F19: 45413 | G19: 557012 | H19: 222001
F20: 45444 | G20: 368536 | H20: 143352
... F38: 45992 | G38: 656876 | H38: 222680
F39: Total | G39: =SUM(G3:G38) -> 17986544 | H39: =SUM(H3:H38) -> 6228883
